pytzdata/__init__.py
pytzdata/_compat.py
pytzdata/_timezones.py
pytzdata/commands/__init__.py
pytzdata/commands/app.py
pytzdata/commands/make.py
pytzdata/commands/zones.py
pytzdata/exceptions.py
pytzdata/version.py
pytzdata/zoneinfo/Africa/Abidjan
pytzdata/zoneinfo/Africa/Accra
pytzdata/zoneinfo/Africa/Addis_Ababa
pytzdata/zoneinfo/Africa/Algiers
pytzdata/zoneinfo/Africa/Asmara
pytzdata/zoneinfo/Africa/Asmera
pytzdata/zoneinfo/Africa/Bamako
pytzdata/zoneinfo/Africa/Bangui
pytzdata/zoneinfo/Africa/Banjul
pytzdata/zoneinfo/Africa/Bissau
pytzdata/zoneinfo/Africa/Blantyre
pytzdata/zoneinfo/Africa/Brazzaville
pytzdata/zoneinfo/Africa/Bujumbura
pytzdata/zoneinfo/Africa/Cairo
pytzdata/zoneinfo/Africa/Casablanca
pytzdata/zoneinfo/Africa/Ceuta
pytzdata/zoneinfo/Africa/Conakry
pytzdata/zoneinfo/Africa/Dakar
pytzdata/zoneinfo/Africa/Dar_es_Salaam
pytzdata/zoneinfo/Africa/Djibouti
pytzdata/zoneinfo/Africa/Douala
pytzdata/zoneinfo/Africa/El_Aaiun
pytzdata/zoneinfo/Africa/Freetown
pytzdata/zoneinfo/Africa/Gaborone
pytzdata/zoneinfo/Africa/Harare
pytzdata/zoneinfo/Africa/Johannesburg
pytzdata/zoneinfo/Africa/Juba
pytzdata/zoneinfo/Africa/Kampala
pytzdata/zoneinfo/Africa/Khartoum
pytzdata/zoneinfo/Africa/Kigali
pytzdata/zoneinfo/Africa/Kinshasa
pytzdata/zoneinfo/Africa/Lagos
pytzdata/zoneinfo/Africa/Libreville
pytzdata/zoneinfo/Africa/Lome
pytzdata/zoneinfo/Africa/Luanda
pytzdata/zoneinfo/Africa/Lubumbashi
pytzdata/zoneinfo/Africa/Lusaka
pytzdata/zoneinfo/Africa/Malabo
pytzdata/zoneinfo/Africa/Maputo
pytzdata/zoneinfo/Africa/Maseru
pytzdata/zoneinfo/Africa/Mbabane
pytzdata/zoneinfo/Africa/Mogadishu
pytzdata/zoneinfo/Africa/Monrovia
pytzdata/zoneinfo/Africa/Nairobi
pytzdata/zoneinfo/Africa/Ndjamena
pytzdata/zoneinfo/Africa/Niamey
pytzdata/zoneinfo/Africa/Nouakchott
pytzdata/zoneinfo/Africa/Ouagadougou
pytzdata/zoneinfo/Africa/Porto-Novo
pytzdata/zoneinfo/Africa/Sao_Tome
pytzdata/zoneinfo/Africa/Timbuktu
pytzdata/zoneinfo/Africa/Tripoli
pytzdata/zoneinfo/Africa/Tunis
pytzdata-2018.9.dist-info/LICENSE
pytzdata-2018.9.dist-info/WHEEL
pytzdata-2018.9.dist-info/METADATA
pytzdata-2018.9.dist-info/RECORD
